Metadata-Version: 2.1
Name: odoo14-addon-account-statement-import-paypal
Version: 14.0.1.0.1
Summary: Import PayPal CSV files as Bank Statements in Odoo
Home-page: https://github.com/OCA/bank-statement-import
Author: Akretion, CorporateHub, Odoo Community Association (OCA)
Author-email: support@odoo-community.org
License: AGPL-3
Platform: UNKNOWN
Classifier: Programming Language :: Python
Classifier: Framework :: Odoo
Classifier: Framework :: Odoo :: 14.0
Classifier: License :: OSI Approved :: GNU Affero General Public License v3
Requires-Python: >=3.6
Requires-Dist: odoo14-addon-account-statement-import
Requires-Dist: odoo14-addon-multi-step-wizard
Requires-Dist: odoo14-addon-web-widget-dropdown-dynamic
Requires-Dist: odoo (<14.1dev,>=14.0a)
